[{"name": 0, "biomass": 0.15543}, {"name": 1, "biomass": 0.0}, {"name": 2, "biomass": 0.18224}, {"name": 3, "biomass": 0.94881}, {"name": 4, "biomass": 2.44454}, {"name": 5, "biomass": 3.58736}, {"name": 6, "biomass": 5.33381}, {"name": 7, "biomass": 6.48596}, {"name": 8, "biomass": 8.02303}, {"name": 9, "biomass": 8.45634}, {"name": 10, "biomass": 8.16618}, {"name": 11, "biomass": 8.84431}, {"name": 12, "biomass": 9.4729}, {"name": 13, "biomass": 9.77076}, {"name": 14, "biomass": 10.50581}, {"name": 15, "biomass": 11.53629}, {"name": 16, "biomass": 12.24864}, {"name": 17, "biomass": 13.43064}, {"name": 18, "biomass": 14.16442}, {"name": 19, "biomass": 14.23012}, {"name": 20, "biomass": 15.02207}, {"name": 21, "biomass": 15.58848}, {"name": 22, "biomass": 15.62636}, {"name": 23, "biomass": 16.27151}, {"name": 24, "biomass": 15.41062}, {"name": 25, "biomass": 15.60143}, {"name": 26, "biomass": 15.72971}, {"name": 27, "biomass": 18.09604}, {"name": 28, "biomass": 17.63964}, {"name": 29, "biomass": 18.01134}, {"name": 30, "biomass": 20.04044}, {"name": 31, "biomass": 20.83871}, {"name": 32, "biomass": 21.65677}, {"name": 33, "biomass": 22.81339}, {"name": 34, "biomass": 21.3494}, {"name": 35, "biomass": 23.55903}, {"name": 36, "biomass": 23.23354}, {"name": 37, "biomass": 23.90977}, {"name": 38, "biomass": 25.38073}, {"name": 39, "biomass": 25.58047}, {"name": 40, "biomass": 27.12206}, {"name": 41, "biomass": 28.33041}, {"name": 42, "biomass": 26.11741}, {"name": 43, "biomass": 26.03818}, {"name": 44, "biomass": 27.57036}, {"name": 45, "biomass": 27.01162}, {"name": 46, "biomass": 26.22179}, {"name": 47, "biomass": 28.76969}, {"name": 48, "biomass": 29.14775}, {"name": 49, "biomass": 30.32188}, {"name": 50, "biomass": 29.08773}, {"name": 51, "biomass": 30.50875}, {"name": 52, "biomass": 31.78067}, {"name": 53, "biomass": 33.11159}, {"name": 54, "biomass": 33.05597}, {"name": 55, "biomass": 34.03722}, {"name": 56, "biomass": 33.82273}, {"name": 57, "biomass": 34.04646}, {"name": 58, "biomass": 31.0124}, {"name": 59, "biomass": 30.49985}, {"name": 60, "biomass": 29.47014}, {"name": 61, "biomass": 29.08141}, {"name": 62, "biomass": 32.1087}, {"name": 63, "biomass": 32.59044}, {"name": 64, "biomass": 32.09121}, {"name": 65, "biomass": 31.96302}, {"name": 66, "biomass": 30.65876}, {"name": 67, "biomass": 29.5428}, {"name": 68, "biomass": 29.46586}, {"name": 69, "biomass": 32.40868}, {"name": 70, "biomass": 32.15917}, {"name": 71, "biomass": 33.68925}, {"name": 72, "biomass": 33.09543}, {"name": 73, "biomass": 34.13133}, {"name": 74, "biomass": 32.07205}, {"name": 75, "biomass": 31.81247}, {"name": 76, "biomass": 33.67371}, {"name": 77, "biomass": 35.86694}, {"name": 78, "biomass": 34.18872}, {"name": 79, "biomass": 35.07539}, {"name": 80, "biomass": 36.35286}, {"name": 81, "biomass": 35.94209}, {"name": 82, "biomass": 34.39007}, {"name": 83, "biomass": 37.1009}, {"name": 84, "biomass": 34.57274}, {"name": 85, "biomass": 37.1806}, {"name": 86, "biomass": 35.20794}, {"name": 87, "biomass": 33.26968}, {"name": 88, "biomass": 34.84926}, {"name": 89, "biomass": 33.65919}, {"name": 90, "biomass": 35.42232}, {"name": 91, "biomass": 34.97525}, {"name": 92, "biomass": 32.83662}, {"name": 93, "biomass": 36.53145}, {"name": 94, "biomass": 33.14097}, {"name": 95, "biomass": 33.50945}, {"name": 96, "biomass": 33.83053}, {"name": 97, "biomass": 34.66403}, {"name": 98, "biomass": 33.69036}, {"name": 99, "biomass": 36.04187}, {"name": 100, "biomass": 36.0853}, {"name": 101, "biomass": 34.9202}, {"name": 102, "biomass": 35.24877}, {"name": 103, "biomass": 35.72317}, {"name": 104, "biomass": 32.66097}, {"name": 105, "biomass": 31.9265}, {"name": 106, "biomass": 32.04048}, {"name": 107, "biomass": 31.11671}, {"name": 108, "biomass": 32.04678}, {"name": 109, "biomass": 34.18729}, {"name": 110, "biomass": 35.74693}, {"name": 111, "biomass": 34.30006}, {"name": 112, "biomass": 37.11397}, {"name": 113, "biomass": 32.62316}, {"name": 114, "biomass": 35.29844}, {"name": 115, "biomass": 34.03082}, {"name": 116, "biomass": 35.52612}, {"name": 117, "biomass": 33.20934}, {"name": 118, "biomass": 34.49921}, {"name": 119, "biomass": 32.01955}, {"name": 120, "biomass": 33.43766}, {"name": 121, "biomass": 33.50986}, {"name": 122, "biomass": 34.66598}, {"name": 123, "biomass": 35.31931}, {"name": 124, "biomass": 34.71001}, {"name": 125, "biomass": 33.59413}, {"name": 126, "biomass": 36.57057}, {"name": 127, "biomass": 33.36881}, {"name": 128, "biomass": 33.97036}, {"name": 129, "biomass": 34.89285}, {"name": 130, "biomass": 37.3298}, {"name": 131, "biomass": 32.82894}, {"name": 132, "biomass": 35.688}, {"name": 133, "biomass": 36.54011}, {"name": 134, "biomass": 34.07874}, {"name": 135, "biomass": 32.1764}, {"name": 136, "biomass": 35.30331}, {"name": 137, "biomass": 36.02853}, {"name": 138, "biomass": 36.60328}, {"name": 139, "biomass": 33.99391}, {"name": 140, "biomass": 35.93896}, {"name": 141, "biomass": 35.82523}, {"name": 142, "biomass": 34.26141}, {"name": 143, "biomass": 33.99725}, {"name": 144, "biomass": 34.47654}, {"name": 145, "biomass": 37.14991}, {"name": 146, "biomass": 35.41405}, {"name": 147, "biomass": 33.82264}, {"name": 148, "biomass": 35.58659}, {"name": 149, "biomass": 36.02381}]